cyecca/__init__.py
cyecca/codegen.py
cyecca/estimate/__init__.py
cyecca/estimate/attitude/__init__.py
cyecca/estimate/attitude/algorithms/__init__.py
cyecca/estimate/attitude/algorithms/common.py
cyecca/estimate/attitude/algorithms/mekf.py
cyecca/estimate/attitude/algorithms/mrp.py
cyecca/estimate/attitude/algorithms/quat.py
cyecca/estimate/attitude/algorithms/sim.py
cyecca/estimate/attitude/estimator.py
cyecca/estimate/attitude/launch.py
cyecca/estimate/attitude/plot.py
cyecca/estimate/attitude/simulator.py
cyecca/graph.py
cyecca/lie/__init__.py
cyecca/lie/base.py
cyecca/lie/direct_product.py
cyecca/lie/group_rn.py
cyecca/lie/group_se2.py
cyecca/lie/group_se23.py
cyecca/lie/group_se3.py
cyecca/lie/group_so2.py
cyecca/lie/group_so3.py
cyecca/models/__init__.py
cyecca/models/bezier.py
cyecca/models/fixedwing.py
cyecca/models/fixedwing_4ch.py
cyecca/models/quadrotor.py
cyecca/models/rdd2.py
cyecca/models/rdd2_loglinear.py
cyecca/sim/__init__.py
cyecca/sim/msgs.py
cyecca/sim/replay.py
cyecca/sim/uros.py
cyecca/symbolic.py
cyecca/util.py
cyecca-0.2.7.dist-info/METADATA
cyecca-0.2.7.dist-info/WHEEL
cyecca-0.2.7.dist-info/licenses/LICENSE
cyecca-0.2.7.dist-info/RECORD
